Products.PloneHotfix20210518-1.6-py2.7-nspkg.pth
Products/PloneHotfix20210518/CHANGES.rst
Products/PloneHotfix20210518/README.txt
Products/PloneHotfix20210518/__init__.py
Products/PloneHotfix20210518/_compat.py
Products/PloneHotfix20210518/content.py
Products/PloneHotfix20210518/difftool.py
Products/PloneHotfix20210518/event.py
Products/PloneHotfix20210518/expressions.py
Products/PloneHotfix20210518/formatter.py
Products/PloneHotfix20210518/genericsetup.py
Products/PloneHotfix20210518/htmltools.py
Products/PloneHotfix20210518/modeleditor.py
Products/PloneHotfix20210518/namedfile.py
Products/PloneHotfix20210518/pa_users.py
Products/PloneHotfix20210518/pas.py
Products/PloneHotfix20210518/portlets.py
Products/PloneHotfix20210518/propertymanager.py
Products/PloneHotfix20210518/publishing.py
Products/PloneHotfix20210518/qi.py
Products/PloneHotfix20210518/skinnable.py
Products/PloneHotfix20210518/supermodel.py
Products/PloneHotfix20210518/theming.py
Products/PloneHotfix20210518/transforms.py
Products/PloneHotfix20210518/utils.py
Products/PloneHotfix20210518/version.txt
Products/PloneHotfix20210518/xmlrpc_dump_instance.py
Products/PloneHotfix20210518/tests/__init__.py
Products/PloneHotfix20210518/tests/testFieldDiff.py
Products/PloneHotfix20210518/tests/testListDiff.py
Products/PloneHotfix20210518/tests/testTextDiff.py
Products/PloneHotfix20210518/tests/test_139_contents.py
Products/PloneHotfix20210518/tests/test_143_fullname.py
Products/PloneHotfix20210518/tests/test_143_namedfile.py
Products/PloneHotfix20210518/tests/test_145_publishing.py
Products/PloneHotfix20210518/tests/test_146_transforms.py
Products/PloneHotfix20210518/tests/test_147_xmlrpc.py
Products/PloneHotfix20210518/tests/test_149_feedparser.py
Products/PloneHotfix20210518/tests/test_150_event_ical.py
Products/PloneHotfix20210518/tests/test_151_underscore_module.py
Products/PloneHotfix20210518/tests/test_152_theming.py
Products/PloneHotfix20210518/tests/test_binarydiff.py
Products.PloneHotfix20210518-1.6.dist-info/METADATA
Products.PloneHotfix20210518-1.6.dist-info/WHEEL
Products.PloneHotfix20210518-1.6.dist-info/entry_points.txt
Products.PloneHotfix20210518-1.6.dist-info/namespace_packages.txt
Products.PloneHotfix20210518-1.6.dist-info/top_level.txt
Products.PloneHotfix20210518-1.6.dist-info/RECORD
